{
    "Brahmaparuss": {
        "Doswiadczenie": "189.218.348 / 189.241.670",
        "Sila": "4000",
        "Obrona": "3670",
        "Zwinnosc": "3490",
        "Wytrzymalosc": "3271",
        "Charyzma": "1506",
        "Walki": "96.249",
        "Zrabowane dobra": "280.928.539.479 krwi"
    },
    "Gawron": {
        "Doswiadczenie": "121.798.812 / 121.825.415",
        "Sila": "2516",
        "Obrona": "2506",
        "Zwinnosc": "2278",
        "Wytrzymalosc": "2003",
        "Charyzma": "1567",
        "Walki": "57.107",
        "Zrabowane dobra": "187.465.070.841 krwi"
    },
    "lux": {
        "Doswiadczenie": "110.973.630 / 111.019.430",
        "Sila": "2379",
        "Obrona": "2871",
        "Zwinnosc": "2123",
        "Wytrzymalosc": "2537",
        "Charyzma": "1886",
        "Walki": "105.532",
        "Zrabowane dobra": "176.895.458.895 krwi"
    },
    "XTurek": {
        "Doswiadczenie": "396.147.999 / 396.236.920",
        "Sila": "4311",
        "Obrona": "3221",
        "Zwinnosc": "3923",
        "Wytrzymalosc": "3733",
        "Charyzma": "2836",
        "Walki": "115.622",
        "Zrabowane dobra": "806.912.421.221 mięsa"
    },
    "Viktor": {
        "Doswiadczenie": "143.362.903 / 143.385.480",
        "Sila": "3007",
        "Obrona": "2992",
        "Zwinnosc": "2620",
        "Wytrzymalosc": "2411",
        "Charyzma": "1572",
        "Walki": "49.768",
        "Zrabowane dobra": "249.170.531.428 krwi"
    },
    "PEON": {
        "Doswiadczenie": "145.839.083 / 145.859.405",
        "Sila": "4793",
        "Obrona": "3288",
        "Zwinnosc": "3003",
        "Wytrzymalosc": "3046",
        "Charyzma": "1772",
        "Walki": "30.668",
        "Zrabowane dobra": "299.040.036.465 mięsa"
    }
}