{
    "Brahmaparuss": {
        "Doswiadczenie": "201.969.618 / 202.000.035",
        "Sila": "4000",
        "Obrona": "3697",
        "Zwinnosc": "3498",
        "Wytrzymalosc": "3301",
        "Charyzma": "1506",
        "Walki": "96.735",
        "Zrabowane dobra": "292.623.617.578 krwi"
    },
    "Gawron": {
        "Doswiadczenie": "125.796.172 / 125.806.295",
        "Sila": "2521",
        "Obrona": "2507",
        "Zwinnosc": "2295",
        "Wytrzymalosc": "2011",
        "Charyzma": "1573",
        "Walki": "57.249",
        "Zrabowane dobra": "190.863.902.280 krwi"
    },
    "lux": {
        "Doswiadczenie": "116.703.928 / 116.745.950",
        "Sila": "2388",
        "Obrona": "2874",
        "Zwinnosc": "2145",
        "Wytrzymalosc": "2543",
        "Charyzma": "1911",
        "Walki": "105.897",
        "Zrabowane dobra": "181.675.732.526 krwi"
    },
    "XTurek": {
        "Doswiadczenie": "422.713.426 / 422.749.320",
        "Sila": "4311",
        "Obrona": "3319",
        "Zwinnosc": "3923",
        "Wytrzymalosc": "3738",
        "Charyzma": "2892",
        "Walki": "115.624",
        "Zrabowane dobra": "833.449.499.005 mięsa"
    },
    "Viktor": {
        "Doswiadczenie": "149.021.731 / 149.063.460",
        "Sila": "3022",
        "Obrona": "2994",
        "Zwinnosc": "2630",
        "Wytrzymalosc": "2428",
        "Charyzma": "1586",
        "Walki": "50.134",
        "Zrabowane dobra": "253.625.412.484 krwi"
    },
    "PEON": {
        "Doswiadczenie": "146.315.534 / 146.345.910",
        "Sila": "4793",
        "Obrona": "3289",
        "Zwinnosc": "3003",
        "Wytrzymalosc": "3046",
        "Charyzma": "1780",
        "Walki": "30.715",
        "Zrabowane dobra": "299.411.974.784 mięsa"
    }
}