{
    "Brahmaparuss": {
        "Doswiadczenie": "164.449.767 / 164.456.860",
        "Sila": "3943",
        "Obrona": "3652",
        "Zwinnosc": "3478",
        "Wytrzymalosc": "3225",
        "Charyzma": "3943",
        "Walki": "95.418",
        "Zrabowane dobra": "258.241.365.263 krwi"
    },
    "Gawron": {
        "Doswiadczenie": "116.347.542 / 116.359.700",
        "Sila": "2511",
        "Obrona": "2505",
        "Zwinnosc": "2254",
        "Wytrzymalosc": "1980",
        "Charyzma": "1549",
        "Walki": "56.874",
        "Zrabowane dobra": "183.211.376.536 krwi"
    },
    "lux": {
        "Doswiadczenie": "102.519.680 / 102.563.730",
        "Sila": "2367",
        "Obrona": "2845",
        "Zwinnosc": "2101",
        "Wytrzymalosc": "2508",
        "Charyzma": "1868",
        "Walki": "103.934",
        "Zrabowane dobra": "170.303.929.550 krwi"
    },
    "XTurek": {
        "Doswiadczenie": "357.479.059 / 357.528.135",
        "Sila": "4311",
        "Obrona": "3071",
        "Zwinnosc": "3858",
        "Wytrzymalosc": "3732",
        "Charyzma": "2836",
        "Walki": "115.615",
        "Zrabowane dobra": "766.972.274.294 mięsa"
    },
    "Viktor": {
        "Doswiadczenie": "138.261.819 / 138.290.660",
        "Sila": "3000",
        "Obrona": "2982",
        "Zwinnosc": "2607",
        "Wytrzymalosc": "2397",
        "Charyzma": "1558",
        "Walki": "49.539",
        "Zrabowane dobra": "245.271.502.575 krwi"
    },
    "PEON": {
        "Doswiadczenie": "144.897.902 / 144.942.660",
        "Sila": "4790",
        "Obrona": "3283",
        "Zwinnosc": "3000",
        "Wytrzymalosc": "3043",
        "Charyzma": "1770",
        "Walki": "30.635",
        "Zrabowane dobra": "297.871.167.557 mięsa"
    }
}