{
    "Brahmaparuss": {
        "Doswiadczenie": "195.348.957 / 195.381.255",
        "Sila": "4000",
        "Obrona": "3670",
        "Zwinnosc": "3493",
        "Wytrzymalosc": "3289",
        "Charyzma": "1506",
        "Walki": "96.505",
        "Zrabowane dobra": "286.706.008.723 krwi"
    },
    "Gawron": {
        "Doswiadczenie": "123.833.421 / 123.857.620",
        "Sila": "2518",
        "Obrona": "2506",
        "Zwinnosc": "2285",
        "Wytrzymalosc": "2006",
        "Charyzma": "1568",
        "Walki": "57.180",
        "Zrabowane dobra": "189.367.385.188 krwi"
    },
    "lux": {
        "Doswiadczenie": "113.754.278 / 113.769.270",
        "Sila": "2383",
        "Obrona": "2871",
        "Zwinnosc": "2131",
        "Wytrzymalosc": "2538",
        "Charyzma": "1907",
        "Walki": "105.800",
        "Zrabowane dobra": "179.430.162.321 krwi"
    },
    "XTurek": {
        "Doswiadczenie": "408.440.141 / 408.526.640",
        "Sila": "4311",
        "Obrona": "3266",
        "Zwinnosc": "3923",
        "Wytrzymalosc": "3733",
        "Charyzma": "2836",
        "Walki": "115.624",
        "Zrabowane dobra": "819.228.560.376 mięsa"
    },
    "Viktor": {
        "Doswiadczenie": "146.085.526 / 146.129.585",
        "Sila": "3008",
        "Obrona": "2994",
        "Zwinnosc": "2625",
        "Wytrzymalosc": "2422",
        "Charyzma": "1581",
        "Walki": "50.033",
        "Zrabowane dobra": "251.495.757.478 krwi"
    },
    "PEON": {
        "Doswiadczenie": "146.055.372 / 146.075.530",
        "Sila": "4793",
        "Obrona": "3288",
        "Zwinnosc": "3003",
        "Wytrzymalosc": "3046",
        "Charyzma": "1775",
        "Walki": "30.705",
        "Zrabowane dobra": "299.168.966.995 mięsa"
    }
}